{"info": {"name": "external", "date_created": "03/08/2022"}, "images": {"id": 1, "width": 800, "height": 1067, "file_name": "0022304_as-0099814.jpg"}, "annotations": [{"id": 2, "image_id": 1, "category_id": "as-0099814", "segmentation": [[[[241, 526], [193, 512], [228, 499], [219, 440], [226, 397], [178, 376], [239, 370], [275, 346], [284, 330], [270, 297], [125, 296], [188, 282], [400, 296], [543, 288], [778, 296], [765, 306], [310, 306], [325, 349], [372, 382], [433, 399], [448, 417], [408, 463], [401, 478], [502, 476], [553, 484], [640, 396], [732, 368], [770, 361], [773, 379], [735, 400], [680, 413], [566, 501], [670, 488], [669, 500], [557, 523], [567, 551], [605, 560], [600, 570], [527, 587], [421, 582], [425, 569], [477, 556], [554, 546], [551, 535], [505, 517], [241, 526]]]], "area": 62536.5, "bbox": [125, 282, 653, 305], "damage": "Scratched", "part": null, "year": 2016, "color": "Black", "level": null, "repair": ["Rear bumper:coating,repair"]}], "categories": {"id": "as-0099814", "supercategory_name": "Full-size car"}}