{"info": {"name": "socar", "date_created": "03/08/2022"}, "images": {"id": 1, "width": 1280, "height": 960, "file_name": "0034157_sc-207940.jpg"}, "annotations": [{"id": 2, "image_id": 1, "category_id": "sc-207940", "segmentation": [[[[377, 699], [379, 633], [593, 621], [694, 598], [749, 500], [786, 440], [819, 461], [777, 528], [749, 631], [565, 661], [561, 675], [377, 699]]]], "area": 25418.0, "bbox": [377, 440, 442, 259], "damage": "Scratched", "part": null, "year": 2018, "color": "White", "level": null, "repair": ["Rear fender(L):coating,sheet_metal", "Rocker panel(L):coating", "Rear door(L):coating,sheet_metal"]}], "categories": {"id": "sc-207940", "supercategory_name": "CityCar"}}