{"info": {"name": "socar", "date_created": "03/08/2022"}, "images": {"id": 1, "width": 1280, "height": 960, "file_name": "0105480_sc-190130.jpg"}, "annotations": [{"id": 2, "image_id": 1, "category_id": "sc-190130", "segmentation": [[[[571, 490], [573, 475], [576, 469], [602, 523], [600, 540], [596, 539], [571, 490]]]], "area": 806.5, "bbox": [571, 469, 31, 71], "damage": "Scratched", "part": null, "year": 2016, "color": "White", "level": null, "repair": ["Front bumper:coating,exchange"]}, {"id": 3, "image_id": 1, "category_id": "sc-190130", "segmentation": [[[[563, 481], [574, 484], [583, 492], [577, 495], [574, 490], [560, 485], [563, 481]]]], "area": 115.0, "bbox": [560, 481, 23, 14], "damage": "Breakage", "part": null, "year": 2016, "color": "White", "level": null, "repair": ["Front bumper:coating,exchange"]}, {"id": 4, "image_id": 1, "category_id": "sc-190130", "segmentation": [[[[577, 385], [584, 388], [581, 408], [578, 405], [577, 390], [577, 385]]]], "area": 105.5, "bbox": [577, 385, 7, 23], "damage": "Scratched", "part": null, "year": 2016, "color": "White", "level": null, "repair": ["Front bumper:coating,exchange"]}, {"id": 5, "image_id": 1, "category_id": "sc-190130", "segmentation": [[[[602, 326], [607, 327], [606, 343], [613, 359], [608, 359], [602, 346], [602, 326]]]], "area": 155.5, "bbox": [602, 326, 11, 33], "damage": "Scratched", "part": null, "year": 2016, "color": "White", "level": null, "repair": ["Front bumper:coating,exchange"]}, {"id": 6, "image_id": 1, "category_id": "sc-190130", "segmentation": [[[[624, 339], [630, 349], [627, 368], [627, 384], [626, 396], [619, 428], [615, 425], [614, 412], [616, 412], [618, 406], [621, 416], [623, 397], [623, 388], [620, 380], [622, 376], [625, 361], [624, 349], [622, 340], [624, 339]]]], "area": 377.5, "bbox": [614, 339, 16, 89], "damage": "Scratched", "part": null, "year": 2016, "color": "White", "level": null, "repair": ["Front bumper:coating,exchange"]}, {"id": 7, "image_id": 1, "category_id": "sc-190130", "segmentation": [[[[612, 447], [616, 447], [616, 452], [612, 452], [612, 447]]]], "area": 20.0, "bbox": [612, 447, 4, 5], "damage": "Scratched", "part": null, "year": 2016, "color": "White", "level": null, "repair": ["Front bumper:coating,exchange"]}, {"id": 8, "image_id": 1, "category_id": "sc-190130", "segmentation": [[[[172, 853], [183, 853], [210, 873], [254, 863], [324, 796], [450, 645], [528, 540], [544, 476], [564, 291], [583, 101], [592, 0], [613, 0], [608, 93], [588, 297], [576, 455], [558, 528], [482, 635], [337, 804], [309, 835], [280, 861], [250, 882], [215, 883], [187, 870], [172, 853]]]], "area": 22132.5, "bbox": [172, 0, 441, 883], "damage": "Separated", "part": null, "year": 2016, "color": "White", "level": null, "repair": ["Front bumper:coating,exchange"]}], "categories": {"id": "sc-190130", "supercategory_name": "Mid-size car"}}