{"info": {"name": "socar", "date_created": "03/08/2022"}, "images": {"id": 1, "width": 1280, "height": 720, "file_name": "0110353_sc-104455.jpg"}, "annotations": [{"id": 2, "image_id": 1, "category_id": "sc-104455", "segmentation": [[[[709, 41], [778, 74], [778, 87], [698, 61], [709, 41]]]], "area": 1391.5, "bbox": [698, 41, 80, 46], "damage": "Scratched", "part": null, "year": 2013, "color": "White", "level": null, "repair": []}, {"id": 3, "image_id": 1, "category_id": "sc-104455", "segmentation": [[[[710, 120], [719, 124], [675, 182], [677, 236], [611, 232], [583, 267], [531, 341], [519, 338], [625, 189], [653, 112], [650, 102], [699, 115], [710, 120]]]], "area": 9095.0, "bbox": [519, 102, 200, 239], "damage": "Scratched", "part": null, "year": 2013, "color": "White", "level": null, "repair": []}, {"id": 4, "image_id": 1, "category_id": "sc-104455", "segmentation": [[[[375, 271], [373, 253], [436, 167], [550, 64], [560, 62], [613, 93], [828, 138], [829, 143], [799, 143], [661, 118], [558, 81], [552, 83], [443, 171], [375, 271]]]], "area": 6327.0, "bbox": [373, 62, 456, 209], "damage": "Separated", "part": null, "year": 2013, "color": "White", "level": null, "repair": []}, {"id": 5, "image_id": 1, "category_id": "sc-104455", "segmentation": [[[[519, 385], [517, 369], [538, 345], [625, 296], [670, 300], [663, 331], [624, 353], [519, 385]]]], "area": 6255.0, "bbox": [517, 296, 153, 89], "damage": "Crushed", "part": null, "year": 2013, "color": "White", "level": null, "repair": []}, {"id": 6, "image_id": 1, "category_id": "sc-104455", "segmentation": [[[[664, 295], [673, 287], [697, 386], [707, 381], [722, 372], [735, 378], [736, 386], [696, 397], [699, 409], [663, 402], [646, 407], [634, 402], [654, 399], [599, 391], [602, 384], [684, 395], [679, 376], [664, 295]]]], "area": 2918.5, "bbox": [599, 287, 137, 122], "damage": "Scratched", "part": null, "year": 2013, "color": "White", "level": null, "repair": []}, {"id": 7, "image_id": 1, "category_id": "sc-104455", "segmentation": [[[[525, 433], [538, 431], [540, 435], [530, 439], [525, 433]]]], "area": 68.0, "bbox": [525, 431, 15, 8], "damage": "Scratched", "part": null, "year": 2013, "color": "White", "level": null, "repair": []}, {"id": 8, "image_id": 1, "category_id": "sc-104455", "segmentation": [[[[562, 535], [569, 530], [614, 561], [657, 572], [656, 601], [644, 616], [639, 614], [651, 586], [648, 581], [593, 556], [567, 544], [562, 535]]]], "area": 1144.5, "bbox": [562, 530, 95, 86], "damage": "Scratched", "part": null, "year": 2013, "color": "White", "level": null, "repair": []}, {"id": 9, "image_id": 1, "category_id": "sc-104455", "segmentation": [[[[868, 467], [875, 473], [808, 505], [808, 538], [797, 577], [799, 595], [818, 607], [839, 636], [822, 633], [786, 587], [776, 574], [777, 529], [788, 505], [793, 480], [868, 467]]]], "area": 4301.0, "bbox": [776, 467, 99, 169], "damage": "Breakage", "part": null, "year": 2013, "color": "White", "level": null, "repair": []}, {"id": 10, "image_id": 1, "category_id": "sc-104455", "segmentation": [[[[1166, 224], [1180, 223], [1172, 230], [1171, 233], [1166, 224]]]], "area": 57.0, "bbox": [1166, 223, 14, 10], "damage": "Scratched", "part": null, "year": 2013, "color": "White", "level": null, "repair": []}], "categories": {"id": "sc-104455", "supercategory_name": "CityCar"}}