{"info": {"name": "socar", "date_created": "03/08/2022"}, "images": {"id": 1, "width": 1280, "height": 960, "file_name": "0167690_sc-194321.jpg"}, "annotations": [{"id": 2, "image_id": 1, "category_id": "sc-194321", "segmentation": [[[[216, 528], [319, 541], [456, 553], [447, 567], [316, 561], [213, 553], [167, 539], [168, 526], [216, 528]]]], "area": 5590.0, "bbox": [167, 526, 289, 41], "damage": "Scratched", "part": null, "year": 2016, "color": "White", "level": null, "repair": []}, {"id": 3, "image_id": 1, "category_id": "sc-194321", "segmentation": [[[[786, 301], [811, 315], [800, 332], [747, 342], [696, 349], [703, 326], [740, 311], [786, 301]]]], "area": 3117.0, "bbox": [696, 301, 115, 48], "damage": "Scratched", "part": null, "year": 2016, "color": "White", "level": null, "repair": []}, {"id": 4, "image_id": 1, "category_id": "sc-194321", "segmentation": [[[[614, 540], [772, 539], [973, 530], [975, 554], [760, 567], [744, 599], [876, 609], [724, 622], [573, 621], [398, 608], [244, 586], [231, 570], [407, 577], [480, 571], [535, 539], [614, 540]]]], "area": 34756.5, "bbox": [231, 530, 744, 92], "damage": "Scratched", "part": null, "year": 2016, "color": "White", "level": null, "repair": []}, {"id": 5, "image_id": 1, "category_id": "sc-194321", "segmentation": [[[[625, 234], [690, 236], [731, 243], [723, 251], [642, 247], [609, 244], [625, 234]]]], "area": 1328.0, "bbox": [609, 234, 122, 17], "damage": "Scratched", "part": null, "year": 2016, "color": "White", "level": null, "repair": []}], "categories": {"id": "sc-194321", "supercategory_name": "Full-size car"}}