{"info": {"name": "socar", "date_created": "03/08/2022"}, "images": {"id": 1, "width": 1280, "height": 960, "file_name": "0190008_sc-195279.jpg"}, "annotations": [{"id": 2, "image_id": 1, "category_id": "sc-195279", "segmentation": [[[[1185, 350], [1181, 356], [1177, 350], [1219, 313], [1236, 293], [1252, 262], [1253, 271], [1227, 316], [1185, 350]]]], "area": 660.5, "bbox": [1177, 262, 76, 94], "damage": "Scratched", "part": null, "year": 2016, "color": "White", "level": null, "repair": ["Rear bumper:coating,repair"]}], "categories": {"id": "sc-195279", "supercategory_name": "Mid-size car"}}