{"info": {"name": "socar", "date_created": "03/08/2022"}, "images": {"id": 1, "width": 800, "height": 725, "file_name": "0193413_sc-226942.jpg"}, "annotations": [{"id": 2, "image_id": 1, "category_id": "sc-226942", "segmentation": [[[[220, 362], [427, 380], [673, 414], [713, 441], [705, 456], [427, 431], [214, 394], [220, 362]]]], "area": 20916.5, "bbox": [214, 362, 499, 94], "damage": "Scratched", "part": null, "year": 2018, "color": "White", "level": null, "repair": ["Rear fender(R):coating,sheet_metal", "Rear door(R):sheet_metal,coating"]}, {"id": 3, "image_id": 1, "category_id": "sc-226942", "segmentation": [[[[649, 303], [800, 331], [800, 384], [668, 409], [526, 422], [388, 403], [292, 380], [121, 349], [27, 278], [71, 276], [227, 262], [380, 282], [649, 303]]]], "area": 75329.0, "bbox": [27, 262, 773, 160], "damage": "Crushed", "part": null, "year": 2018, "color": "White", "level": null, "repair": ["Rear fender(R):coating,sheet_metal", "Rear door(R):sheet_metal,coating"]}], "categories": {"id": "sc-226942", "supercategory_name": "CityCar"}}