{"info": {"name": "socar", "date_created": "03/08/2022"}, "images": {"id": 1, "width": 1280, "height": 960, "file_name": "0242999_sc-112550.jpg"}, "annotations": [{"id": 2, "image_id": 1, "category_id": "sc-112550", "segmentation": [[[[654, 449], [699, 437], [723, 424], [733, 431], [712, 444], [661, 458], [654, 449]]]], "area": 821.0, "bbox": [654, 424, 79, 34], "damage": "Scratched", "part": null, "year": 2014, "color": "White", "level": null, "repair": []}, {"id": 3, "image_id": 1, "category_id": "sc-112550", "segmentation": [[[[1058, 369], [1075, 369], [1069, 381], [1022, 406], [1010, 419], [1083, 397], [1133, 378], [1173, 359], [1166, 375], [1120, 402], [1072, 419], [1012, 435], [972, 445], [962, 477], [910, 491], [935, 451], [964, 424], [1058, 369]]]], "area": 6931.0, "bbox": [910, 359, 263, 132], "damage": "Scratched", "part": null, "year": 2014, "color": "White", "level": null, "repair": []}], "categories": {"id": "sc-112550", "supercategory_name": "Full-size car"}}