{"info": {"name": "external", "date_created": "03/08/2022"}, "images": {"id": 1, "width": 800, "height": 1067, "file_name": "0278533_as-0097487.jpg"}, "annotations": [{"id": 2, "image_id": 1, "category_id": "as-0097487", "segmentation": [[[[362, 765], [358, 744], [362, 723], [418, 725], [387, 752], [362, 765]]]], "area": 1396.0, "bbox": [358, 723, 60, 42], "damage": "Breakage", "part": null, "year": 2019, "color": "Black", "level": null, "repair": ["Rear bumper:coating,exchange"]}, {"id": 3, "image_id": 1, "category_id": "as-0097487", "segmentation": [[[[356, 802], [355, 771], [361, 767], [364, 774], [361, 800], [356, 802]]]], "area": 227.0, "bbox": [355, 767, 9, 35], "damage": "Separated", "part": null, "year": 2019, "color": "Black", "level": null, "repair": ["Rear bumper:coating,exchange"]}, {"id": 4, "image_id": 1, "category_id": "as-0097487", "segmentation": [[[[365, 798], [376, 793], [389, 815], [401, 837], [404, 862], [397, 920], [389, 921], [382, 906], [377, 883], [387, 849], [365, 798]]]], "area": 2262.0, "bbox": [365, 793, 39, 128], "damage": "Breakage", "part": null, "year": 2019, "color": "Black", "level": null, "repair": ["Rear bumper:coating,exchange"]}, {"id": 5, "image_id": 1, "category_id": "as-0097487", "segmentation": [[[[373, 794], [369, 789], [419, 757], [402, 775], [384, 791], [373, 794]]]], "area": 349.5, "bbox": [369, 757, 50, 37], "damage": "Separated", "part": null, "year": 2019, "color": "Black", "level": null, "repair": ["Rear bumper:coating,exchange"]}, {"id": 6, "image_id": 1, "category_id": "as-0097487", "segmentation": [[[[273, 443], [283, 442], [321, 545], [359, 605], [331, 576], [294, 505], [273, 443]]]], "area": 1458.5, "bbox": [273, 442, 86, 163], "damage": "Separated", "part": null, "year": 2019, "color": "Black", "level": null, "repair": ["Rear bumper:coating,exchange"]}, {"id": 7, "image_id": 1, "category_id": "as-0097487", "segmentation": [[[[310, 457], [394, 457], [419, 455], [435, 558], [437, 658], [531, 656], [570, 689], [456, 725], [445, 804], [460, 841], [467, 903], [396, 918], [311, 917], [262, 891], [288, 871], [321, 879], [398, 833], [360, 773], [332, 716], [339, 692], [310, 457]]]], "area": 55801.0, "bbox": [262, 455, 308, 463], "damage": "Scratched", "part": null, "year": 2019, "color": "Black", "level": null, "repair": ["Rear bumper:coating,exchange"]}], "categories": {"id": "as-0097487", "supercategory_name": "Mid-size car"}}