{"info": {"name": "external", "date_created": "03/08/2022"}, "images": {"id": 1, "width": 800, "height": 1067, "file_name": "0289059_as-0094625.jpg"}, "annotations": [{"id": 1, "image_id": 1, "category_id": "as-0094625", "segmentation": [[[[775, 622], [800, 625], [799, 739], [749, 791], [710, 790], [734, 747], [773, 726], [783, 706], [717, 708], [733, 661], [775, 622]]]], "area": 8613.5, "bbox": [710, 622, 90, 169], "damage": "Scratched", "part": null, "year": 2013, "color": "Black", "level": null, "repair": ["Front bumper:coating,exchange", "Head lights:exchange", "Front fender(L):sheet_metal,coating"]}, {"id": 2, "image_id": 1, "category_id": "as-0094625", "segmentation": [[[[754, 599], [795, 585], [800, 618], [765, 632], [754, 599]]]], "area": 1366.0, "bbox": [754, 585, 46, 47], "damage": "Breakage", "part": null, "year": 2013, "color": "Black", "level": null, "repair": ["Front bumper:coating,exchange", "Head lights:exchange", "Front fender(L):sheet_metal,coating"]}], "categories": {"id": "as-0094625", "supercategory_name": "Full-size car"}}