{"info": {"name": "socar", "date_created": "03/08/2022"}, "images": {"id": 1, "width": 960, "height": 720, "file_name": "0321962_sc-206062.jpg"}, "annotations": [{"id": 2, "image_id": 1, "category_id": "sc-206062", "segmentation": [[[[290, 470], [305, 466], [676, 506], [690, 534], [424, 503], [301, 484], [290, 470]]]], "area": 9262.5, "bbox": [290, 466, 400, 68], "damage": "Scratched", "part": null, "year": 2016, "color": "White", "level": null, "repair": []}, {"id": 3, "image_id": 1, "category_id": "sc-206062", "segmentation": [[[[226, 412], [220, 385], [206, 354], [216, 319], [261, 308], [281, 314], [270, 351], [226, 412]]]], "area": 4315.0, "bbox": [206, 308, 75, 104], "damage": "Crushed", "part": null, "year": 2016, "color": "White", "level": null, "repair": []}, {"id": 4, "image_id": 1, "category_id": "sc-206062", "segmentation": [[[[202, 462], [193, 484], [179, 460], [195, 429], [219, 419], [216, 432], [202, 462]]]], "area": 1111.5, "bbox": [179, 419, 40, 65], "damage": "Crushed", "part": null, "year": 2016, "color": "White", "level": null, "repair": []}, {"id": 5, "image_id": 1, "category_id": "sc-206062", "segmentation": [[[[118, 37], [138, 44], [135, 68], [121, 66], [118, 37]]]], "area": 450.5, "bbox": [118, 37, 20, 31], "damage": "Scratched", "part": null, "year": 2016, "color": "White", "level": null, "repair": []}, {"id": 6, "image_id": 1, "category_id": "sc-206062", "segmentation": [[[[20, 49], [42, 40], [49, 67], [44, 76], [20, 49]]]], "area": 504.0, "bbox": [20, 40, 29, 36], "damage": "Scratched", "part": null, "year": 2016, "color": "White", "level": null, "repair": []}, {"id": 7, "image_id": 1, "category_id": "sc-206062", "segmentation": [[[[356, 653], [359, 642], [374, 644], [417, 657], [549, 676], [605, 685], [607, 702], [519, 694], [392, 681], [372, 672], [356, 653]]]], "area": 5834.5, "bbox": [356, 642, 251, 60], "damage": "Scratched", "part": null, "year": 2016, "color": "White", "level": null, "repair": []}, {"id": 8, "image_id": 1, "category_id": "sc-206062", "segmentation": [[[[544, 697], [358, 680], [276, 663], [224, 664], [208, 664], [203, 655], [219, 652], [272, 654], [326, 664], [368, 672], [472, 683], [536, 694], [544, 697]]]], "area": 2752.5, "bbox": [203, 652, 341, 45], "damage": "Separated", "part": null, "year": 2016, "color": "White", "level": null, "repair": []}, {"id": 9, "image_id": 1, "category_id": "sc-206062", "segmentation": [[[[295, 537], [315, 540], [317, 563], [300, 566], [295, 537]]]], "area": 481.0, "bbox": [295, 537, 22, 29], "damage": "Scratched", "part": null, "year": 2016, "color": "White", "level": null, "repair": []}, {"id": 10, "image_id": 1, "category_id": "sc-206062", "segmentation": [[[[400, 562], [415, 561], [419, 565], [425, 578], [410, 580], [400, 562]]]], "area": 291.5, "bbox": [400, 561, 25, 19], "damage": "Crushed", "part": null, "year": 2016, "color": "White", "level": null, "repair": []}, {"id": 11, "image_id": 1, "category_id": "sc-206062", "segmentation": [[[[501, 545], [551, 532], [582, 539], [579, 554], [537, 555], [504, 554], [501, 545]]]], "area": 1350.0, "bbox": [501, 532, 81, 23], "damage": "Crushed", "part": null, "year": 2016, "color": "White", "level": null, "repair": []}], "categories": {"id": "sc-206062", "supercategory_name": "Mid-size car"}}