{"info": {"name": "socar", "date_created": "03/08/2022"}, "images": {"id": 1, "width": 1199, "height": 693, "file_name": "0361268_sc-164037.jpg"}, "annotations": [{"id": 2, "image_id": 1, "category_id": "sc-164037", "segmentation": [[[[382, 332], [381, 265], [522, 252], [596, 219], [679, 232], [771, 286], [784, 347], [873, 404], [933, 445], [900, 466], [824, 429], [746, 388], [594, 353], [463, 360], [388, 361], [382, 332]]]], "area": 53913.0, "bbox": [381, 219, 552, 247], "damage": "Crushed", "part": null, "year": 2016, "color": "White", "level": null, "repair": ["Rear fender(L):sheet_metal,coating"]}, {"id": 3, "image_id": 1, "category_id": "sc-164037", "segmentation": [[[[360, 279], [393, 255], [456, 243], [485, 254], [593, 242], [692, 228], [697, 244], [477, 291], [481, 315], [635, 298], [635, 312], [584, 324], [621, 330], [829, 313], [833, 337], [764, 348], [855, 374], [911, 401], [962, 456], [897, 473], [838, 438], [778, 408], [713, 384], [630, 367], [572, 367], [506, 365], [444, 378], [384, 398], [360, 279]]]], "area": 49911.0, "bbox": [360, 228, 602, 245], "damage": "Scratched", "part": null, "year": 2016, "color": "White", "level": null, "repair": ["Rear fender(L):sheet_metal,coating"]}], "categories": {"id": "sc-164037", "supercategory_name": "Full-size car"}}