{"info": {"name": "socar", "date_created": "03/08/2022"}, "images": {"id": 1, "width": 1280, "height": 1280, "file_name": "0362157_sc-219893.jpg"}, "annotations": [{"id": 2, "image_id": 1, "category_id": "sc-219893", "segmentation": [[[[372, 491], [381, 494], [385, 494], [385, 497], [377, 497], [370, 494], [372, 491]]]], "area": 51.0, "bbox": [370, 491, 15, 6], "damage": "Separated", "part": null, "year": 2016, "color": "White", "level": null, "repair": []}], "categories": {"id": "sc-219893", "supercategory_name": "Mid-size car"}}