{"info": {"name": "socar", "date_created": "03/08/2022"}, "images": {"id": 1, "width": 800, "height": 1428, "file_name": "0365425_sc-145609.jpg"}, "annotations": [{"id": 2, "image_id": 1, "category_id": "sc-145609", "segmentation": [[[[378, 628], [520, 615], [613, 593], [662, 649], [656, 702], [640, 728], [527, 747], [392, 720], [336, 709], [341, 662], [378, 628]]]], "area": 35718.5, "bbox": [336, 593, 326, 154], "damage": "Crushed", "part": null, "year": 2017, "color": "White", "level": null, "repair": ["Front bumper:coating,sheet_metal,exchange", "Rear door(R):sheet_metal,coating"]}, {"id": 3, "image_id": 1, "category_id": "sc-145609", "segmentation": [[[[300, 674], [337, 659], [390, 665], [397, 649], [444, 657], [457, 675], [486, 663], [521, 660], [634, 647], [670, 652], [665, 676], [647, 710], [625, 699], [572, 699], [573, 713], [498, 723], [479, 712], [416, 722], [395, 699], [358, 698], [370, 726], [360, 741], [346, 716], [323, 715], [310, 708], [304, 695], [300, 674]]]], "area": 19220.0, "bbox": [300, 647, 370, 94], "damage": "Scratched", "part": null, "year": 2017, "color": "White", "level": null, "repair": ["Front bumper:coating,sheet_metal,exchange", "Rear door(R):sheet_metal,coating"]}, {"id": 4, "image_id": 1, "category_id": "sc-145609", "segmentation": [[[[340, 621], [346, 601], [366, 604], [358, 624], [340, 621]]]], "area": 401.0, "bbox": [340, 601, 26, 23], "damage": "Scratched", "part": null, "year": 2017, "color": "White", "level": null, "repair": ["Front bumper:coating,sheet_metal,exchange", "Rear door(R):sheet_metal,coating"]}, {"id": 5, "image_id": 1, "category_id": "sc-145609", "segmentation": [[[[358, 528], [358, 480], [372, 475], [369, 528], [358, 528]]]], "area": 627.5, "bbox": [358, 475, 14, 53], "damage": "Scratched", "part": null, "year": 2017, "color": "White", "level": null, "repair": ["Front bumper:coating,sheet_metal,exchange", "Rear door(R):sheet_metal,coating"]}, {"id": 6, "image_id": 1, "category_id": "sc-145609", "segmentation": [[[[401, 271], [427, 271], [423, 300], [403, 298], [401, 271]]]], "area": 645.0, "bbox": [401, 271, 26, 29], "damage": "Scratched", "part": null, "year": 2017, "color": "White", "level": null, "repair": ["Front bumper:coating,sheet_metal,exchange", "Rear door(R):sheet_metal,coating"]}, {"id": 7, "image_id": 1, "category_id": "sc-145609", "segmentation": [[[[555, 0], [523, 452], [495, 656], [490, 716], [490, 776], [468, 1069], [465, 1131], [456, 1156], [473, 1160], [543, 1157], [567, 1149], [576, 1053], [609, 845], [638, 736], [664, 656], [650, 582], [634, 491], [632, 438], [684, 261], [786, 2], [791, 1], [721, 179], [658, 369], [642, 444], [643, 479], [650, 542], [672, 617], [672, 675], [646, 751], [623, 850], [588, 1025], [576, 1122], [576, 1145], [568, 1159], [550, 1165], [464, 1168], [450, 1205], [441, 1252], [429, 1259], [417, 1256], [441, 1189], [440, 1160], [446, 1132], [485, 747], [487, 653], [516, 394], [529, 105], [532, 0], [555, 0]]]], "area": 28481.5, "bbox": [417, 0, 374, 1259], "damage": "Separated", "part": null, "year": 2017, "color": "White", "level": null, "repair": ["Front bumper:coating,sheet_metal,exchange", "Rear door(R):sheet_metal,coating"]}], "categories": {"id": "sc-145609", "supercategory_name": "Compact car"}}