{"info": {"name": "socar", "date_created": "03/08/2022"}, "images": {"id": 1, "width": 1067, "height": 600, "file_name": "0417637_sc-135432.jpg"}, "annotations": [{"id": 2, "image_id": 1, "category_id": "sc-135432", "segmentation": [[[[765, 523], [702, 537], [559, 554], [484, 555], [474, 518], [479, 482], [496, 467], [545, 444], [586, 425], [606, 384], [646, 330], [710, 303], [776, 305], [831, 280], [865, 236], [896, 212], [914, 244], [890, 319], [863, 408], [836, 476], [765, 523]]]], "area": 73020.0, "bbox": [474, 212, 440, 343], "damage": "Crushed", "part": null, "year": 2018, "color": "White", "level": null, "repair": ["Rear door(R):sheet_metal,exchange"]}, {"id": 3, "image_id": 1, "category_id": "sc-135432", "segmentation": [[[[301, 306], [302, 318], [295, 339], [283, 340], [264, 325], [257, 309], [265, 303], [301, 306]]]], "area": 1188.0, "bbox": [257, 303, 45, 37], "damage": "Scratched", "part": null, "year": 2018, "color": "White", "level": null, "repair": ["Rear door(R):sheet_metal,exchange"]}, {"id": 4, "image_id": 1, "category_id": "sc-135432", "segmentation": [[[[969, 220], [964, 239], [941, 284], [933, 278], [941, 236], [969, 220]]]], "area": 970.0, "bbox": [933, 220, 36, 64], "damage": "Scratched", "part": null, "year": 2018, "color": "White", "level": null, "repair": ["Rear door(R):sheet_metal,exchange"]}], "categories": {"id": "sc-135432", "supercategory_name": "Compact car"}}