{"info": {"name": "socar", "date_created": "03/08/2022"}, "images": {"id": 1, "width": 960, "height": 1280, "file_name": "0447647_sc-228447.jpg"}, "annotations": [{"id": 2, "image_id": 1, "category_id": "sc-228447", "segmentation": [[[[386, 505], [403, 491], [431, 488], [463, 489], [464, 505], [450, 519], [389, 509], [386, 505]]]], "area": 1742.0, "bbox": [386, 488, 78, 31], "damage": "Scratched", "part": null, "year": 2017, "color": "White", "level": null, "repair": []}, {"id": 3, "image_id": 1, "category_id": "sc-228447", "segmentation": [[[[370, 615], [372, 607], [456, 612], [458, 619], [370, 615]]]], "area": 645.0, "bbox": [370, 607, 88, 12], "damage": "Scratched", "part": null, "year": 2017, "color": "White", "level": null, "repair": []}, {"id": 4, "image_id": 1, "category_id": "sc-228447", "segmentation": [[[[357, 685], [357, 679], [406, 681], [405, 686], [382, 687], [357, 685]]]], "area": 303.0, "bbox": [357, 679, 49, 8], "damage": "Scratched", "part": null, "year": 2017, "color": "White", "level": null, "repair": []}, {"id": 5, "image_id": 1, "category_id": "sc-228447", "segmentation": [[[[384, 702], [384, 696], [398, 697], [396, 699], [384, 702]]]], "area": 51.0, "bbox": [384, 696, 14, 6], "damage": "Scratched", "part": null, "year": 2017, "color": "White", "level": null, "repair": []}, {"id": 6, "image_id": 1, "category_id": "sc-228447", "segmentation": [[[[375, 774], [390, 742], [424, 733], [450, 745], [480, 759], [493, 785], [500, 797], [499, 806], [478, 803], [464, 801], [438, 773], [416, 782], [400, 806], [387, 824], [371, 840], [365, 818], [375, 774]]]], "area": 6324.0, "bbox": [365, 733, 135, 107], "damage": "Scratched", "part": null, "year": 2017, "color": "White", "level": null, "repair": []}], "categories": {"id": "sc-228447", "supercategory_name": "CityCar"}}