{"info": {"name": "socar", "date_created": "03/08/2022"}, "images": {"id": 1, "width": 1280, "height": 960, "file_name": "0450117_sc-180064.jpg"}, "annotations": [{"id": 2, "image_id": 1, "category_id": "sc-180064", "segmentation": [[[[324, 380], [405, 334], [449, 336], [502, 359], [525, 388], [527, 422], [554, 478], [552, 548], [544, 600], [485, 671], [403, 690], [384, 667], [324, 594], [300, 491], [324, 380]]]], "area": 68578.0, "bbox": [300, 334, 254, 356], "damage": "Crushed", "part": null, "year": 2016, "color": "White", "level": null, "repair": ["Bonnet:coating,exchange", "Front bumper:coating,exchange"]}, {"id": 3, "image_id": 1, "category_id": "sc-180064", "segmentation": [[[[506, 4], [537, 0], [546, 0], [562, 25], [562, 69], [569, 369], [574, 460], [579, 551], [564, 888], [562, 922], [549, 938], [497, 960], [504, 888], [516, 710], [537, 499], [520, 325], [520, 199], [506, 4]]]], "area": 47320.0, "bbox": [497, 0, 82, 960], "damage": "Separated", "part": null, "year": 2016, "color": "White", "level": null, "repair": ["Bonnet:coating,exchange", "Front bumper:coating,exchange"]}, {"id": 4, "image_id": 1, "category_id": "sc-180064", "segmentation": [[[[499, 461], [579, 437], [576, 429], [572, 417], [598, 402], [618, 418], [641, 390], [662, 392], [662, 400], [673, 416], [672, 503], [656, 691], [645, 793], [616, 864], [593, 875], [615, 805], [622, 756], [623, 734], [656, 520], [637, 450], [638, 429], [603, 462], [601, 497], [578, 508], [571, 532], [552, 543], [513, 537], [518, 515], [458, 550], [431, 542], [456, 507], [499, 461]]]], "area": 24986.5, "bbox": [431, 390, 242, 485], "damage": "Scratched", "part": null, "year": 2016, "color": "White", "level": null, "repair": ["Bonnet:coating,exchange", "Front bumper:coating,exchange"]}, {"id": 5, "image_id": 1, "category_id": "sc-180064", "segmentation": [[[[620, 493], [674, 506], [675, 494], [682, 467], [671, 463], [656, 457], [657, 454], [659, 453], [668, 451], [668, 434], [680, 431], [690, 425], [690, 419], [690, 396], [694, 370], [705, 355], [722, 358], [734, 376], [734, 389], [750, 425], [728, 471], [728, 490], [732, 513], [734, 530], [725, 537], [713, 551], [671, 548], [609, 547], [569, 534], [559, 503], [620, 493]]]], "area": 15369.5, "bbox": [559, 355, 191, 196], "damage": "Breakage", "part": null, "year": 2016, "color": "White", "level": null, "repair": ["Bonnet:coating,exchange", "Front bumper:coating,exchange"]}], "categories": {"id": "sc-180064", "supercategory_name": "Mid-size car"}}